pydrodynamics/__init__.py
pydrodynamics/dynamics.py
pydrodynamics/environment.py
pydrodynamics/params.py
pydrodynamics/thrusters.py
pydrodynamics/utils.py
pydrodynamics/vehicle.py
pydrodynamics-1.0.2.dist-info/licenses/LICENSE
pydrodynamics-1.0.2.dist-info/METADATA
pydrodynamics-1.0.2.dist-info/WHEEL
pydrodynamics-1.0.2.dist-info/top_level.txt
pydrodynamics-1.0.2.dist-info/RECORD
