Metadata-Version: 2.4
Name: pydrodynamics
Version: 1.0.2
Summary: A Python package for simulating underwater hydrodynamics
Author-email: Muhammad Fauzan <muhammadfauzanaristyaputra@gmail.com>
License: MIT License
Project-URL: Source, https://github.com/MFauzanAP/pydrodynamics
Keywords: hydrodynamics,mathematical,model,simulation,underwater,fossen
Classifier: License :: OSI Approved :: MIT License
Classifier: Programming Language :: Python
Classifier: Programming Language :: Python :: 3
Requires-Python: >=3.9
License-File: LICENSE
Requires-Dist: numpy
Requires-Dist: scipy
Requires-Dist: pyyaml
Requires-Dist: dataclasses
Dynamic: license-file
